{
  "schema_version": "safe_drl_v1",
  "kind": "drl_baseline_run",
  "algo": "ppo",
  "regime": "high_embb",
  "shield": "static",
  "seed": 43,
  "static_floor": 50,
  "device": "cpu",
  "lib": {
    "stable_baselines3": "2.6.0",
    "gymnasium": "1.1.1",
    "torch": "2.5.1+cu124",
    "numpy": "2.2.6"
  },
  "evidence": {
    "total_timesteps_requested": 300000,
    "total_timesteps_consumed": 303104,
    "checkpoint_path": "/home/huangxiaolin/safe_drl_oran/02_models/ppo_high_embb_static_s43.zip",
    "checkpoint_exists": true,
    "checkpoint_bytes": 199371,
    "vecnorm_path": "/home/huangxiaolin/safe_drl_oran/02_models/ppo_high_embb_static_s43_vecnorm.pkl",
    "n_eval_episodes": 20,
    "wall_seconds": 107.6,
    "train_cum_urllc_violations": 2012,
    "train_steps": 303104,
    "train_shield_corrections": 237378,
    "lib": {
      "stable_baselines3": "2.6.0",
      "gymnasium": "1.1.1",
      "torch": "2.5.1+cu124",
      "numpy": "2.2.6"
    },
    "device": "cpu",
    "seed": 43
  },
  "train_metrics": {
    "reward_curve": [
      [
        5000,
        253.2735875
      ],
      [
        10000,
        253.76929187500002
      ],
      [
        15000,
        253.6031817638889
      ],
      [
        20000,
        253.6865454479167
      ],
      [
        25000,
        253.61723665000002
      ],
      [
        30000,
        253.69195769
      ],
      [
        35000,
        253.82276595000002
      ],
      [
        40000,
        254.04986451000002
      ],
      [
        45000,
        254.10644548999997
      ],
      [
        50000,
        253.99117037
      ],
      [
        55000,
        254.82219481999996
      ],
      [
        60000,
        255.22649976999998
      ],
      [
        65000,
        256.16975986
      ],
      [
        70000,
        257.43965528
      ],
      [
        75000,
        258.59148387000005
      ],
      [
        80000,
        259.87818272000004
      ],
      [
        85000,
        261.59519156000005
      ],
      [
        90000,
        263.27318549999995
      ],
      [
        95000,
        265.01987013
      ],
      [
        100000,
        267.95974072
      ],
      [
        105000,
        270.88319048
      ],
      [
        110000,
        274.79045663
      ],
      [
        115000,
        278.57196789
      ],
      [
        120000,
        282.55323002
      ],
      [
        125000,
        288.05140912999997
      ],
      [
        130000,
        290.91525762000003
      ],
      [
        135000,
        293.72918778
      ],
      [
        140000,
        295.87082682999994
      ],
      [
        145000,
        297.44092162
      ],
      [
        150000,
        298.9626541
      ],
      [
        155000,
        300.1112177
      ],
      [
        160000,
        300.77494549999994
      ],
      [
        165000,
        302.18062821
      ],
      [
        170000,
        303.23529583
      ],
      [
        175000,
        304.00027778
      ],
      [
        180000,
        305.03071195
      ],
      [
        185000,
        305.47547267000004
      ],
      [
        190000,
        306.41304680999997
      ],
      [
        195000,
        307.46410137000004
      ],
      [
        200000,
        308.56762713999996
      ],
      [
        205000,
        310.26210777
      ],
      [
        210000,
        311.40014166000003
      ],
      [
        215000,
        312.25963969000003
      ],
      [
        220000,
        313.11456359
      ],
      [
        225000,
        313.53197481999996
      ],
      [
        230000,
        313.52482735
      ],
      [
        235000,
        313.67656445999995
      ],
      [
        240000,
        313.77360516
      ],
      [
        245000,
        313.81900124000003
      ],
      [
        250000,
        313.93942188
      ],
      [
        255000,
        314.06486497
      ],
      [
        260000,
        314.09450224
      ],
      [
        265000,
        314.34053712
      ],
      [
        270000,
        314.54034648
      ],
      [
        275000,
        314.94044789
      ],
      [
        280000,
        315.42084489999996
      ],
      [
        285000,
        316.02934580999994
      ],
      [
        290000,
        316.2834108
      ],
      [
        295000,
        316.33413116
      ],
      [
        300000,
        316.04859303999996
      ]
    ],
    "safety_curve": [
      [
        5000,
        27,
        5000
      ],
      [
        10000,
        58,
        10000
      ],
      [
        15000,
        92,
        15000
      ],
      [
        20000,
        120,
        20000
      ],
      [
        25000,
        145,
        25000
      ],
      [
        30000,
        170,
        30000
      ],
      [
        35000,
        196,
        35000
      ],
      [
        40000,
        227,
        40000
      ],
      [
        45000,
        255,
        45000
      ],
      [
        50000,
        286,
        50000
      ],
      [
        55000,
        315,
        55000
      ],
      [
        60000,
        344,
        60000
      ],
      [
        65000,
        373,
        65000
      ],
      [
        70000,
        401,
        70000
      ],
      [
        75000,
        429,
        75000
      ],
      [
        80000,
        458,
        80000
      ],
      [
        85000,
        484,
        85000
      ],
      [
        90000,
        522,
        90000
      ],
      [
        95000,
        556,
        95000
      ],
      [
        100000,
        583,
        100000
      ],
      [
        105000,
        609,
        105000
      ],
      [
        110000,
        640,
        110000
      ],
      [
        115000,
        671,
        115000
      ],
      [
        120000,
        701,
        120000
      ],
      [
        125000,
        733,
        125000
      ],
      [
        130000,
        770,
        130000
      ],
      [
        135000,
        810,
        135000
      ],
      [
        140000,
        843,
        140000
      ],
      [
        145000,
        874,
        145000
      ],
      [
        150000,
        907,
        150000
      ],
      [
        155000,
        940,
        155000
      ],
      [
        160000,
        973,
        160000
      ],
      [
        165000,
        1005,
        165000
      ],
      [
        170000,
        1042,
        170000
      ],
      [
        175000,
        1080,
        175000
      ],
      [
        180000,
        1115,
        180000
      ],
      [
        185000,
        1150,
        185000
      ],
      [
        190000,
        1186,
        190000
      ],
      [
        195000,
        1222,
        195000
      ],
      [
        200000,
        1257,
        200000
      ],
      [
        205000,
        1290,
        205000
      ],
      [
        210000,
        1329,
        210000
      ],
      [
        215000,
        1370,
        215000
      ],
      [
        220000,
        1404,
        220000
      ],
      [
        225000,
        1438,
        225000
      ],
      [
        230000,
        1471,
        230000
      ],
      [
        235000,
        1507,
        235000
      ],
      [
        240000,
        1543,
        240000
      ],
      [
        245000,
        1579,
        245000
      ],
      [
        250000,
        1619,
        250000
      ],
      [
        255000,
        1660,
        255000
      ],
      [
        260000,
        1696,
        260000
      ],
      [
        265000,
        1731,
        265000
      ],
      [
        270000,
        1766,
        270000
      ],
      [
        275000,
        1801,
        275000
      ],
      [
        280000,
        1836,
        280000
      ],
      [
        285000,
        1872,
        285000
      ],
      [
        290000,
        1912,
        290000
      ],
      [
        295000,
        1954,
        295000
      ],
      [
        300000,
        1989,
        300000
      ]
    ],
    "train_violation_rate": 0.006637985641891892,
    "train_shield_correction_rate": 0.7831569362331081,
    "final_train_ep_rew": 316.04859303999996
  },
  "eval_metrics": {
    "reward": 1.6158007450020286,
    "urllc_violation_rate": 0.00525,
    "embb_sla_rate": 0.7357499999999999,
    "mmtc_sla_rate": 0.28374999999999995,
    "fairness": 0.7887207100190606,
    "shield_correction_rate": 0.99975
  },
  "eval_per_episode": [
    {
      "reward": 1.6168165927927856,
      "urllc_violation_rate": 0.005,
      "embb_sla_rate": 0.75,
      "mmtc_sla_rate": 0.28,
      "fairness": 0.7815177308788986,
      "shield_correction_rate": 1.0
    },
    {
      "reward": 1.6152691767816412,
      "urllc_violation_rate": 0.005,
      "embb_sla_rate": 0.74,
      "mmtc_sla_rate": 0.275,
      "fairness": 0.7890816352296542,
      "shield_correction_rate": 1.0
    },
    {
      "reward": 1.6116071717372358,
      "urllc_violation_rate": 0.005,
      "embb_sla_rate": 0.735,
      "mmtc_sla_rate": 0.265,
      "fairness": 0.7838627738473591,
      "shield_correction_rate": 1.0
    },
    {
      "reward": 1.6025644251709814,
      "urllc_violation_rate": 0.01,
      "embb_sla_rate": 0.745,
      "mmtc_sla_rate": 0.315,
      "fairness": 0.7942171461157023,
      "shield_correction_rate": 1.0
    },
    {
      "reward": 1.5997024500843207,
      "urllc_violation_rate": 0.01,
      "embb_sla_rate": 0.705,
      "mmtc_sla_rate": 0.3,
      "fairness": 0.7896564481173995,
      "shield_correction_rate": 1.0
    },
    {
      "reward": 1.5941618329222929,
      "urllc_violation_rate": 0.015,
      "embb_sla_rate": 0.71,
      "mmtc_sla_rate": 0.275,
      "fairness": 0.7913746494210302,
      "shield_correction_rate": 1.0
    },
    {
      "reward": 1.6333629818818212,
      "urllc_violation_rate": 0.0,
      "embb_sla_rate": 0.76,
      "mmtc_sla_rate": 0.28,
      "fairness": 0.787351047944561,
      "shield_correction_rate": 1.0
    },
    {
      "reward": 1.627845523428124,
      "urllc_violation_rate": 0.0,
      "embb_sla_rate": 0.73,
      "mmtc_sla_rate": 0.285,
      "fairness": 0.7919452829165126,
      "shield_correction_rate": 1.0
    },
    {
      "reward": 1.6275731480104192,
      "urllc_violation_rate": 0.0,
      "embb_sla_rate": 0.745,
      "mmtc_sla_rate": 0.265,
      "fairness": 0.7844466199764037,
      "shield_correction_rate": 1.0
    },
    {
      "reward": 1.6116968933674354,
      "urllc_violation_rate": 0.005,
      "embb_sla_rate": 0.74,
      "mmtc_sla_rate": 0.245,
      "fairness": 0.7890816352296542,
      "shield_correction_rate": 1.0
    },
    {
      "reward": 1.617328821226427,
      "urllc_violation_rate": 0.005,
      "embb_sla_rate": 0.73,
      "mmtc_sla_rate": 0.27,
      "fairness": 0.7885057933491899,
      "shield_correction_rate": 1.0
    },
    {
      "reward": 1.6129903559421173,
      "urllc_violation_rate": 0.005,
      "embb_sla_rate": 0.745,
      "mmtc_sla_rate": 0.28,
      "fairness": 0.790802961557091,
      "shield_correction_rate": 1.0
    },
    {
      "reward": 1.6212917864083118,
      "urllc_violation_rate": 0.005,
      "embb_sla_rate": 0.725,
      "mmtc_sla_rate": 0.32,
      "fairness": 0.7896564481173995,
      "shield_correction_rate": 1.0
    },
    {
      "reward": 1.616326672594235,
      "urllc_violation_rate": 0.005,
      "embb_sla_rate": 0.725,
      "mmtc_sla_rate": 0.28,
      "fairness": 0.7902302256739476,
      "shield_correction_rate": 0.995
    },
    {
      "reward": 1.6138736354064458,
      "urllc_violation_rate": 0.005,
      "embb_sla_rate": 0.745,
      "mmtc_sla_rate": 0.28,
      "fairness": 0.7850294876701305,
      "shield_correction_rate": 1.0
    },
    {
      "reward": 1.6019140390354785,
      "urllc_violation_rate": 0.01,
      "embb_sla_rate": 0.74,
      "mmtc_sla_rate": 0.295,
      "fairness": 0.7890816352296542,
      "shield_correction_rate": 1.0
    },
    {
      "reward": 1.6220147011439965,
      "urllc_violation_rate": 0.005,
      "embb_sla_rate": 0.76,
      "mmtc_sla_rate": 0.305,
      "fairness": 0.7890816352296542,
      "shield_correction_rate": 1.0
    },
    {
      "reward": 1.6152312465607486,
      "urllc_violation_rate": 0.005,
      "embb_sla_rate": 0.705,
      "mmtc_sla_rate": 0.305,
      "fairness": 0.7942171461157023,
      "shield_correction_rate": 1.0
    },
    {
      "reward": 1.6319815275581515,
      "urllc_violation_rate": 0.0,
      "embb_sla_rate": 0.735,
      "mmtc_sla_rate": 0.27,
      "fairness": 0.7861922625316099,
      "shield_correction_rate": 1.0
    },
    {
      "reward": 1.622461917987603,
      "urllc_violation_rate": 0.005,
      "embb_sla_rate": 0.745,
      "mmtc_sla_rate": 0.285,
      "fairness": 0.7890816352296542,
      "shield_correction_rate": 1.0
    }
  ],
  "paper_usable": true
}